django_autoresponse_middleware/__init__.py
django_autoresponse_middleware-0.1.0.dist-info/LICENSE.txt
django_autoresponse_middleware-0.1.0.dist-info/METADATA
django_autoresponse_middleware-0.1.0.dist-info/WHEEL
django_autoresponse_middleware-0.1.0.dist-info/top_level.txt
django_autoresponse_middleware-0.1.0.dist-info/RECORD
