Metadata-Version: 2.1
Name: django-autoresponse-middleware
Version: 0.1.0
Summary: ...
Author: Daniel Pepper
License: The MIT License (MIT)
Project-URL: Homepage, https://github.com/dpep/django-autoresponse-middleware
Classifier: Framework :: Django
Classifier: License :: OSI Approved :: MIT License
Requires-Python: >=3
License-File: LICENSE.txt
Requires-Dist: django
Provides-Extra: test
Requires-Dist: isort >=5.13 ; extra == 'test'
Requires-Dist: pytest >=8.2 ; extra == 'test'
Requires-Dist: pytest-django ; extra == 'test'
Requires-Dist: setuptools >=61 ; extra == 'test'
